LICENSE
MANIFEST.in
README.rst
pyproject.toml
setup.cfg
setup.py
api_data_cache/__init__.py
api_data_cache/mixins.py
api_data_cache/search_filter.py
django_api_data_cache.egg-info/PKG-INFO
django_api_data_cache.egg-info/SOURCES.txt
django_api_data_cache.egg-info/dependency_links.txt
django_api_data_cache.egg-info/requires.txt
django_api_data_cache.egg-info/top_level.txt